enems/__init__.py
enems/enems.py
enems/example_data/ensemble_set_75.pickle
enems/example_data/ensemble_set_75_obs_a.pickle
enems/example_data/ensemble_set_75_obs_b.pickle
enems/example_data/ensemble_set_75_obs_c.pickle
en_ems-0.2.2.dist-info/METADATA
en_ems-0.2.2.dist-info/WHEEL
en_ems-0.2.2.dist-info/top_level.txt
en_ems-0.2.2.dist-info/RECORD
