Metadata-Version: 2.1
Name: en-ems
Version: 0.2.2
Summary: A package for selecting ensemble members using entropy theory
Home-page: https://github.com/adlzanchetta/en-ems
Author: Andre D. L. Zanchetta
Author-email: adlzanchetta@gmail.com
License: UNKNOWN
Platform: UNKNOWN
Classifier: Programming Language :: Python
Classifier: Programming Language :: Python :: 3
Classifier: Programming Language :: Python :: 3.7
Classifier: License :: OSI Approved :: MIT License
Classifier: Operating System :: OS Independent
Requires-Dist: pyitlib (==0.2.2)
Requires-Dist: scikit-learn (<1,>=0.23)
Requires-Dist: pandas (>=1.3)
